{"api-examples.md":"CCwCbSlY","changelog.md":"yOFA6BSp","index.md":"DCji0sQ0","installed.md":"BCrKT0aw","markdown-examples.md":"s5sEJ_Ti","src_functions_chunk.md":"CQRYeTyl","src_functions_clone.md":"B65_lKS_","src_functions_copy.md":"RdGuLgk7","src_functions_debounce.md":"DAuKJmzA","src_functions_identitycodevalid.md":"MZ6r9n6G","src_functions_isarray.md":"CqlSc0yG","src_functions_isboolean.md":"nlfVVk5l","src_functions_ischinesephone.md":"C0S7LVKx","src_functions_isdate.md":"DF9ssiez","src_functions_isempty.md":"CDBmwYvM","src_functions_isemptystr.md":"Dqccj8zF","src_functions_isequalarray.md":"bZH-6yiM","src_functions_iserror.md":"CxEE_jNb","src_functions_isfalsy.md":"B58hmFDO","src_functions_isfalsynon0.md":"DRcFeg1t","src_functions_isfunction.md":"D2OlrBU0","src_functions_ishttpurl.md":"Hw2Vywyp","src_functions_isnull.md":"CygDPUPg","src_functions_isnullish.md":"DLKEuNOV","src_functions_isnumber.md":"7FmS8PTc","src_functions_isnumerical.md":"VMvK39MU","src_functions_isobject.md":"DONdCzfM","src_functions_isprimitive.md":"C9nel_lX","src_functions_isregexp.md":"DZ8gFBP2","src_functions_isstring.md":"B-wGeb9w","src_functions_issymbol.md":"rVInvwyX","src_functions_istruthy.md":"DqLLFdw2","src_functions_isundefined.md":"CQb6GUbs","src_functions_modulo.md":"Dh-OUm1b","src_functions_normalizemoney.md":"BPC8UbQu","src_functions_randomnum.md":"BL2ZEu3C","src_functions_randomstr.md":"CypGKWxH","src_functions_remainder.md":"lLuFxY3g","src_functions_removerepeat.md":"pnmooZjB","src_functions_repeatrun.md":"Cih7xqWL","src_functions_throttle.md":"B-rUVbBs","src_functions_type.md":"DP_R75-2","src_functions_uuid.md":"CXKtc8NF","src_globals.md":"Cb8v2myv","src_interfaces_repeatoptions.md":"OMwoRGMh","src_readme.md":"CDZRtAOm","src_type-aliases_repeatfn.md":"C_ps17ZP","src_type-aliases_stoprepeat.md":"D1X5eER5","what-is-petite-utils.md":"BC-swkGz"}
